imageobfuscator/__init__.py
imageobfuscator/__main__.py
imageobfuscator_shantih19-1.0.3.dist-info/LICENSE.txt
imageobfuscator_shantih19-1.0.3.dist-info/METADATA
imageobfuscator_shantih19-1.0.3.dist-info/WHEEL
imageobfuscator_shantih19-1.0.3.dist-info/entry_points.txt
imageobfuscator_shantih19-1.0.3.dist-info/top_level.txt
imageobfuscator_shantih19-1.0.3.dist-info/RECORD
