Metadata-Version: 2.1
Name: imageobfuscator-shantih19
Version: 1.0.3
Summary: Encode and decode data in an image using a password
Home-page: https://github.com/shantih19/imageobfuscator
Author: shantih19
Author-email: shantih19@gmail.com
License: UNKNOWN
Project-URL: Bug Tracker, https://github.com/shantih19/imageobfuscator/issues
Platform: UNKNOWN
Classifier: Programming Language :: Python :: 3
Classifier: License :: Other/Proprietary License
Classifier: Operating System :: OS Independent
Requires-Python: >=3.6
License-File: LICENSE.txt
Requires-Dist: pillow
